rezume_theme_onepage/__init__.py
rezume_theme_onepage/assets/rezume.hbs
rezume_theme_onepage/assets/style.css
rezume_theme_onepage-0.1.0.dist-info/WHEEL
rezume_theme_onepage-0.1.0.dist-info/METADATA
rezume_theme_onepage-0.1.0.dist-info/RECORD
